b3j0f/__init__.py
b3j0f/aop/joinpoint.py
b3j0f/aop/version.py
b3j0f/aop/advice.py
b3j0f/aop/__init__.py
b3j0f/aop/test/joinpoint.py
b3j0f/aop/test/advice.py
b3j0f/aop/test/__init__.py
b3j0f/aop/advice/core.py
b3j0f/aop/advice/__init__.py
b3j0f/aop/advice/utils.py
b3j0f/aop/advice/test/core.py
b3j0f/aop/advice/test/__init__.py
b3j0f/aop/advice/test/utils.py
b3j0f/aop/joinpoint/core.py
b3j0f/aop/joinpoint/__init__.py
b3j0f/aop/joinpoint/test/core.py
b3j0f/aop/joinpoint/test/__init__.py
b3j0f.aop-0.8.4.dist-info/DESCRIPTION.rst
b3j0f.aop-0.8.4.dist-info/RECORD
b3j0f.aop-0.8.4.dist-info/metadata.json
b3j0f.aop-0.8.4.dist-info/top_level.txt
b3j0f.aop-0.8.4.dist-info/METADATA
b3j0f.aop-0.8.4.dist-info/WHEEL
